{"PubmedArticle": [{"MedlineCitation": {"SpaceFlightMission": [], "OtherID": [], "InvestigatorList": [], "OtherAbstract": [], "CitationSubset": ["IM"], "KeywordList": [], "GeneralNote": [], "PMID": "10563967", "DateCompleted": {"Year": "2000", "Month": "09", "Day": "12"}, "DateRevised": {"Year": "2019", "Month": "07", "Day": "23"}, "Article": {"ArticleDate": [], "Language": ["eng"], "ELocationID": [], "Journal": {"ISSN": "0021-8561", "JournalIssue": {"Volume": "47", "Issue": "2", "PubDate": {"Year": "1999", "Month": "Feb"}}, "Title": "Journal of agricultural and food chemistry", "ISOAbbreviation": "J Agric Food Chem"}, "ArticleTitle": "Isolation, characterization, and biological activity of naphthoquinones from Calceolaria andina L.", "Pagination": {"StartPage": "770", "EndPage": "775", "MedlinePgn": "770-5"}, "Abstract": {"AbstractText": ["Two compounds recognized as responsible for the insecticidal activity of extracts of Calceolaria andina L. (Scrophulariaceae) have been isolated and characterized as 2-(1, 1-dimethylprop-2-enyl)-3-hydroxy-1,4-naphthoquinone and the corresponding acetate, 2-acetoxy-3-(1,1-dimethylprop-2-enyl)-1, 4-naphthoquinone. Their activities against 29 pest species and 9 beneficial species of arthropod from a total of 11 orders have been determined. Activities against homopteran and acarine species are of the same order as those of established pesticides, and, significantly, no cross-resistance is observed for strains resistant to established classes of insecticide. Mammalian toxicities are low."]}, "AuthorList": [{"AffiliationInfo": [{"Identifier": [], "Affiliation": "Jodrell Laboratory, Royal Botanic Gardens, Kew, Surrey, United Kingdom. Bhupinder.khambay@bbscr.ac.uk"}], "Identifier": [], "LastName": "Khambay", "ForeName": "B P", "Initials": "BP"}, {"AffiliationInfo": [], "Identifier": [], "LastName": "Batty", "ForeName": "D", "Initials": "D"}, {"AffiliationInfo": [], "Identifier": [], "LastName": "Cahill", "ForeName": "M", "Initials": "M"}, {"AffiliationInfo": [], "Identifier": [], "LastName": "Denholm", "ForeName": "I", "Initials": "I"}, {"AffiliationInfo": [], "Identifier": [], "LastName": "Mead-Briggs", "ForeName": "M", "Initials": "M"}, {"AffiliationInfo": [], "Identifier": [], "LastName": "Vinall", "ForeName": "S", "Initials": "S"}, {"AffiliationInfo": [], "Identifier": [], "LastName": "Niemeyer", "ForeName": "H M", "Initials": "HM"}, {"AffiliationInfo": [], "Identifier": [], "LastName": "Simmonds", "ForeName": "M S", "Initials": "MS"}], "PublicationTypeList": ["Journal Article", "Research Support, Non-U.S. Gov't"]}, "MedlineJournalInfo": {"Country": "United States", "MedlineTA": "J Agric Food Chem", "NlmUniqueID": "0374755", "ISSNLinking": "0021-8561"}, "ChemicalList": [{"RegistryNumber": "0", "NameOfSubstance": "Insecticides"}, {"RegistryNumber": "0", "NameOfSubstance": "Naphthoquinones"}], "MeshHeadingList": [{"QualifierName": [], "DescriptorName": "Animals"}, {"QualifierName": [], "DescriptorName": "Insecta"}, {"QualifierName": ["isolation & purification", "toxicity"], "DescriptorName": "Insecticides"}, {"QualifierName": [], "DescriptorName": "Lethal Dose 50"}, {"QualifierName": ["isolation & purification", "toxicity"], "DescriptorName": "Naphthoquinones"}, {"QualifierName": ["chemistry"], "DescriptorName": "Plant Leaves"}, {"QualifierName": ["chemistry"], "DescriptorName": "Plants, Medicinal"}, {"QualifierName": [], "DescriptorName": "Rats"}]}, "PubmedData": {"ReferenceList": [], "History": [{"Year": "1999", "Month": "11", "Day": "24", "Hour": "9", "Minute": "0"}, {"Year": "2000", "Month": "9", "Day": "19", "Hour": "11", "Minute": "1"}, {"Year": "1999", "Month": "11", "Day": "24", "Hour": "9", "Minute": "0"}], "PublicationStatus": "ppublish", "ArticleIdList": ["10563967", "10.1021/jf980769j", "jf980769j"]}}], "PubmedBookArticle": []}