{"PubmedArticle": [{"MedlineCitation": {"CitationSubset": ["OM"], "KeywordList": [["CHEMISTRY, PHARMACEUTICAL", "EXPERIMENTAL LAB STUDY", "PLANTS, MEDICINAL", "STEROIDS"]], "GeneralNote": [], "InvestigatorList": [], "OtherID": [], "OtherAbstract": [], "SpaceFlightMission": [], "PMID": "14140203", "DateCompleted": {"Year": "1996", "Month": "12", "Day": "01"}, "DateRevised": {"Year": "2018", "Month": "12", "Day": "01"}, "Article": {"Language": ["rus"], "ELocationID": [], "ArticleDate": [], "Journal": {"JournalIssue": {"Volume": "17", "PubDate": {"Year": "1963", "Month": "Nov"}}, "Title": "Meditsinskaia promyshlennost' SSSR", "ISOAbbreviation": "Med Prom SSSR"}, "ArticleTitle": "[ON THE SEPARATION OF GLYCOALKALOIDS OF SOLANUM AVICULARE IN THE PRODUCTION OF SOLASODINE].", "Pagination": {"StartPage": "35", "EndPage": "39", "MedlinePgn": "35-9"}, "AuthorList": [{"AffiliationInfo": [], "Identifier": [], "LastName": "ZEIFMAN", "ForeName": "V I", "Initials": "VI"}, {"AffiliationInfo": [], "Identifier": [], "LastName": "KRISTALL", "ForeName": "Z B", "Initials": "ZB"}, {"AffiliationInfo": [], "Identifier": [], "LastName": "POTKOV", "ForeName": "G A", "Initials": "GA"}, {"AffiliationInfo": [], "Identifier": [], "LastName": "SILMAN", "ForeName": "A I", "Initials": "AI"}, {"AffiliationInfo": [], "Identifier": [], "LastName": "SHAPOSHNIKOVA", "ForeName": "G A", "Initials": "GA"}], "PublicationTypeList": ["Journal Article"], "VernacularTitle": "O SEPARITOVANII GLIKOALKALOIDOV PASLENA PTICH'EGO V PROIZVODSTVE SOLASODINA."}, "MedlineJournalInfo": {"Country": "Russia (Federation)", "MedlineTA": "Med Prom SSSR", "NlmUniqueID": "1305622"}, "ChemicalList": [{"RegistryNumber": "0", "NameOfSubstance": "Solanaceous Alkaloids"}, {"RegistryNumber": "0", "NameOfSubstance": "Steroids"}, {"RegistryNumber": "L40Y453Y96", "NameOfSubstance": "solasodine"}], "MeshHeadingList": [{"QualifierName": [], "DescriptorName": "Chemistry, Pharmaceutical"}, {"QualifierName": [], "DescriptorName": "Plants"}, {"QualifierName": [], "DescriptorName": "Plants, Medicinal"}, {"QualifierName": [], "DescriptorName": "Research"}, {"QualifierName": [], "DescriptorName": "Solanaceous Alkaloids"}, {"QualifierName": [], "DescriptorName": "Solanum"}, {"QualifierName": [], "DescriptorName": "Steroids"}]}, "PubmedData": {"ReferenceList": [], "History": [{"Year": "1963", "Month": "11", "Day": "1"}, {"Year": "1963", "Month": "11", "Day": "1", "Hour": "0", "Minute": "1"}, {"Year": "1963", "Month": "11", "Day": "1", "Hour": "0", "Minute": "0"}], "PublicationStatus": "ppublish", "ArticleIdList": ["14140203"]}}], "PubmedBookArticle": []}