{"PubmedArticle": [{"MedlineCitation": {"SpaceFlightMission": [], "OtherID": [], "InvestigatorList": [], "OtherAbstract": [], "CitationSubset": ["IM"], "KeywordList": [], "GeneralNote": [], "PMID": "14510616", "DateCompleted": {"Year": "2004", "Month": "03", "Day": "04"}, "DateRevised": {"Year": "2015", "Month": "11", "Day": "19"}, "Article": {"ArticleDate": [], "Language": ["eng"], "ELocationID": [], "Journal": {"ISSN": "0163-3864", "JournalIssue": {"Volume": "66", "Issue": "9", "PubDate": {"Year": "2003", "Month": "Sep"}}, "Title": "Journal of natural products", "ISOAbbreviation": "J Nat Prod"}, "ArticleTitle": "Tricin from a malagasy connaraceous plant with potent antihistaminic activity.", "Pagination": {"StartPage": "1273", "EndPage": "1275", "MedlinePgn": "1273-5"}, "Abstract": {"AbstractText": ["The bioassay-guided separation of a Malagasy plant, Agelaea pentagyna, led to the isolation of a flavonoid, tricin (1), with potent inhibitory activity toward exocytosis from antigen-stimulated rat leukemia basophils (RBL-2H3). The structure-activity relationships among structurally related natural and synthetic flavonoids are also discussed."]}, "AuthorList": [{"AffiliationInfo": [{"Identifier": [], "Affiliation": "Department of Pharmacognosy, Division of Medicinal Chemistry, Graduate School of Biomedical Sciences, Hiroshima University, 1-2-3 Kasumi, Minami-ku, Hiroshima 734-8551, Japan."}], "Identifier": [], "LastName": "Kuwabara", "ForeName": "Hidenori", "Initials": "H"}, {"AffiliationInfo": [], "Identifier": [], "LastName": "Mouri", "ForeName": "Kyoko", "Initials": "K"}, {"AffiliationInfo": [], "Identifier": [], "LastName": "Otsuka", "ForeName": "Hideaki", "Initials": "H"}, {"AffiliationInfo": [], "Identifier": [], "LastName": "Kasai", "ForeName": "Ryoji", "Initials": "R"}, {"AffiliationInfo": [], "Identifier": [], "LastName": "Yamasaki", "ForeName": "Kazuo", "Initials": "K"}], "PublicationTypeList": ["Journal Article"]}, "MedlineJournalInfo": {"Country": "United States", "MedlineTA": "J Nat Prod", "NlmUniqueID": "7906882", "ISSNLinking": "0163-3864"}, "ChemicalList": [{"RegistryNumber": "0", "NameOfSubstance": "Flavonoids"}, {"RegistryNumber": "0", "NameOfSubstance": "Histamine H1 Antagonists"}, {"RegistryNumber": "D51JZL38TQ", "NameOfSubstance": "tricin"}], "MeshHeadingList": [{"QualifierName": [], "DescriptorName": "Animals"}, {"QualifierName": ["drug effects"], "DescriptorName": "Basophils"}, {"QualifierName": ["chemistry"], "DescriptorName": "Connaraceae"}, {"QualifierName": ["chemistry", "isolation & purification", "pharmacology"], "DescriptorName": "Flavonoids"}, {"QualifierName": ["chemistry", "isolation & purification", "pharmacology"], "DescriptorName": "Histamine H1 Antagonists"}, {"QualifierName": [], "DescriptorName": "Leukemia"}, {"QualifierName": [], "DescriptorName": "Molecular Structure"}, {"QualifierName": ["chemistry"], "DescriptorName": "Plants, Medicinal"}, {"QualifierName": [], "DescriptorName": "Rats"}, {"QualifierName": [], "DescriptorName": "Structure-Activity Relationship"}]}, "PubmedData": {"ReferenceList": [], "History": [{"Year": "2003", "Month": "9", "Day": "27", "Hour": "5", "Minute": "0"}, {"Year": "2004", "Month": "3", "Day": "5", "Hour": "5", "Minute": "0"}, {"Year": "2003", "Month": "9", "Day": "27", "Hour": "5", "Minute": "0"}], "PublicationStatus": "ppublish", "ArticleIdList": ["14510616", "10.1021/np030020p"]}}], "PubmedBookArticle": []}