{"PubmedArticle": [{"MedlineCitation": {"SpaceFlightMission": [], "OtherID": [], "InvestigatorList": [], "OtherAbstract": [], "CitationSubset": ["IM"], "KeywordList": [], "GeneralNote": [], "PMID": "17323995", "DateCompleted": {"Year": "2007", "Month": "05", "Day": "24"}, "DateRevised": {"Year": "2007", "Month": "04", "Day": "27"}, "Article": {"ArticleDate": [{"Year": "2007", "Month": "02", "Day": "27"}], "Language": ["eng"], "ELocationID": [], "Journal": {"ISSN": "0163-3864", "JournalIssue": {"Volume": "70", "Issue": "4", "PubDate": {"Year": "2007", "Month": "Apr"}}, "Title": "Journal of natural products", "ISOAbbreviation": "J Nat Prod"}, "ArticleTitle": "Limonoids from the seeds of the marine mangrove Xylocarpus granatum.", "Pagination": {"StartPage": "682", "EndPage": "685", "MedlinePgn": "682-5"}, "Abstract": {"AbstractText": ["Five new limonoids, granaxylocarpins A-E (1-5), were isolated from the seeds of the Chinese marine mangrove Xylocarpus granatum. Granaxylocarpins A (1) and B (2) are mexicanolide-type limonoids with a 9,10-seco skeleton, and granaxylocarpin C (3) possesses an 8alpha,30alpha-epoxy ring and a rare 1,29-oxygen bridge. The structures of these limonoids were characterized on the basis of extensive spectroscopic methods and single-crystal X-ray diffraction analysis performed on 4. The structure of xyloccensin U (4a) was revised as 4b by comparison with granaxylocarpin D (4). The cytotoxicity of these isolates was evaluated against the P-388 and A-549 tumor cell lines."]}, "AuthorList": [{"AffiliationInfo": [{"Identifier": [], "Affiliation": "State Key Laboratory of Drug Research, Institute of Materia Medica, Shanghai Institutes for Biological Sciences, Chinese Academy of Sciences, 555 Zu Chong Zhi Road, Zhangjiang Hi-Tech Park, Shanghai 201203, People's Republic of China."}], "Identifier": [], "LastName": "Yin", "ForeName": "Sheng", "Initials": "S"}, {"AffiliationInfo": [], "Identifier": [], "LastName": "Wang", "ForeName": "Xiao-Ning", "Initials": "XN"}, {"AffiliationInfo": [], "Identifier": [], "LastName": "Fan", "ForeName": "Cheng-Qi", "Initials": "CQ"}, {"AffiliationInfo": [], "Identifier": [], "LastName": "Lin", "ForeName": "Li-Ping", "Initials": "LP"}, {"AffiliationInfo": [], "Identifier": [], "LastName": "Ding", "ForeName": "Jian", "Initials": "J"}, {"AffiliationInfo": [], "Identifier": [], "LastName": "Yue", "ForeName": "Jian-Min", "Initials": "JM"}], "PublicationTypeList": ["Journal Article", "Research Support, Non-U.S. Gov't"]}, "MedlineJournalInfo": {"Country": "United States", "MedlineTA": "J Nat Prod", "NlmUniqueID": "7906882", "ISSNLinking": "0163-3864"}, "ChemicalList": [{"RegistryNumber": "0", "NameOfSubstance": "Antineoplastic Agents, Phytogenic"}, {"RegistryNumber": "0", "NameOfSubstance": "Drugs, Chinese Herbal"}, {"RegistryNumber": "0", "NameOfSubstance": "Limonins"}], "MeshHeadingList": [{"QualifierName": [], "DescriptorName": "Animals"}, {"QualifierName": ["chemistry", "isolation & purification", "pharmacology"], "DescriptorName": "Antineoplastic Agents, Phytogenic"}, {"QualifierName": [], "DescriptorName": "Crystallography, X-Ray"}, {"QualifierName": [], "DescriptorName": "Drug Screening Assays, Antitumor"}, {"QualifierName": ["chemistry", "isolation & purification", "pharmacology"], "DescriptorName": "Drugs, Chinese Herbal"}, {"QualifierName": [], "DescriptorName": "Humans"}, {"QualifierName": [], "DescriptorName": "Leukemia P388"}, {"QualifierName": ["chemistry", "isolation & purification", "pharmacology"], "DescriptorName": "Limonins"}, {"QualifierName": ["chemistry"], "DescriptorName": "Meliaceae"}, {"QualifierName": [], "DescriptorName": "Mice"}, {"QualifierName": [], "DescriptorName": "Molecular Structure"}, {"QualifierName": ["chemistry"], "DescriptorName": "Plants, Medicinal"}, {"QualifierName": ["chemistry"], "DescriptorName": "Seeds"}]}, "PubmedData": {"ReferenceList": [], "History": [{"Year": "2007", "Month": "2", "Day": "28", "Hour": "9", "Minute": "0"}, {"Year": "2007", "Month": "5", "Day": "26", "Hour": "9", "Minute": "0"}, {"Year": "2007", "Month": "2", "Day": "28", "Hour": "9", "Minute": "0"}], "PublicationStatus": "ppublish", "ArticleIdList": ["17323995", "10.1021/np060632k"]}}], "PubmedBookArticle": []}