{"PubmedArticle": [{"MedlineCitation": {"SpaceFlightMission": [], "OtherID": [], "InvestigatorList": [], "OtherAbstract": [], "CitationSubset": [], "KeywordList": [["Tirumala hills", "economic importance", "endemic plants", "medicinal importance"]], "GeneralNote": [], "PMID": "18317578", "DateCompleted": {"Year": "2010", "Month": "06", "Day": "09"}, "DateRevised": {"Year": "2024", "Month": "05", "Day": "11"}, "Article": {"ArticleDate": [{"Year": "2008", "Month": "01", "Day": "27"}], "Language": ["eng"], "ELocationID": [], "Journal": {"ISSN": "0973-2063", "JournalIssue": {"Volume": "2", "Issue": "6", "PubDate": {"Year": "2008", "Month": "Jan", "Day": "27"}}, "Title": "Bioinformation", "ISOAbbreviation": "Bioinformation"}, "ArticleTitle": "A database on endemic plants at Tirumala hills in India.", "Pagination": {"StartPage": "260", "EndPage": "262", "MedlinePgn": "260-2"}, "Abstract": {"AbstractText": ["Medicinal plants play an important role in health care. The use of medicinal plants for treatment is growing in view of cost and non-compliance of modern medicine as in case of non-communicable diseases. Plants such as Boswellia, ovalifoliolata, Cycas beddomei, Pimpinella tirupatiensis, Pterocarpus santalinus, Shorea thumbuggaia, Syzygium alternifolium, Terminalia pallida are endemic to Tirumala hills of seshachalam range falling under the Eastern Ghats of India. These plants species have medicinal properties such as anti-tumorogenic, anti-microbial, purgative, hypoglycemic, abortificient, analgesic, anti-septic, anti-pyretic and anti-inflammatory. We created a database named DEPTH in an attempt to communicate data of these plants to the scientific community. DEPTH contains data on scientific name, vernacular name, family name, morphological description, economic importance, known medicinal compounds and medicinal importance.", "http://svimstpt.ap.nic.in/MedicinalPlants/mainpage.htm."]}, "AuthorList": [{"AffiliationInfo": [{"Identifier": [], "Affiliation": "Sri Venkateswara Institute of Medical Sciences, Tirupati. yakheen@rediffmail.com"}], "Identifier": [], "LastName": "Latheef", "ForeName": "Shaik Abdul", "Initials": "SA"}, {"AffiliationInfo": [], "Identifier": [], "LastName": "Prasad", "ForeName": "Beerkam", "Initials": "B"}, {"AffiliationInfo": [], "Identifier": [], "LastName": "Bavaji", "ForeName": "Middi", "Initials": "M"}, {"AffiliationInfo": [], "Identifier": [], "LastName": "Subramanyam", "ForeName": "Gangapatnam", "Initials": "G"}], "PublicationTypeList": ["Journal Article"]}, "MedlineJournalInfo": {"Country": "Singapore", "MedlineTA": "Bioinformation", "NlmUniqueID": "101258255", "ISSNLinking": "0973-2063"}}, "PubmedData": {"ReferenceList": [{"ReferenceList": [], "Reference": [{"Citation": "Farnsworth NR, et al. Bulletin of the WHO. 1985;63:965.", "ArticleIdList": ["PMC2536466", "3879679"]}, {"Citation": "Kala CP. Ethnobot Res Appl. 2005;3:267."}, {"Citation": "Kala CP, et al. J Ethnobiol Ethnomed. 2006;2:32.", "ArticleIdList": ["0"]}, {"Citation": "http://www.ciagri.usp.br/planmedi/planger.htm"}, {"Citation": "http://www.frlht.org.in/meta"}, {"Citation": "http://www.fao.org/docrep/W7261E/W7261e09.htm"}, {"Citation": "http://www.google.com"}, {"Citation": "http://envis-eptri.ap.nic.in"}, {"Citation": "Reddy VLN, et al. Cheminform. 2007;35:931."}, {"Citation": "Chandrasekhar T, et al. Biosciences. 2005;60:505.", "ArticleIdList": ["16042352"]}, {"Citation": "Prabhakar CS, Rao KR. Photosyn Res. 1981;2:297.", "ArticleIdList": ["24470249"]}, {"Citation": "Muniappan R, Viraktamath CA. Current Science. 2006;91:868."}, {"Citation": "Prakash E, et al. Current Science. 2001;81:1239."}, {"Citation": "Bakshu LM, et al. Flavour and Fragrance Journal. 2002;17:413."}, {"Citation": "Krishnaveni KS, Srinivasa Rao JV. Asian Nat Prod Res. 2000;2:219.", "ArticleIdList": ["11256696"]}, {"Citation": "Krishnaveni KS, Srinivasa Rao JV. Chem Pharm Bull. 2000;48:1373.", "ArticleIdList": ["10993243"]}, {"Citation": "Cho JY, et al. Biol Pharm Bull. 2001;24:167.", "ArticleIdList": ["11217086"]}, {"Citation": "Krishnaveni KS, Srinivasa Rao JV. Fitoterapia. 2000;71:10.", "ArticleIdList": ["11449463"]}, {"Citation": "Rao BK, et al. J Ethnopharmacol. 2001;74:69.", "ArticleIdList": ["0"]}, {"Citation": "Manjunatha BK. Indian J Pharmacol. 2006;68:115."}, {"Citation": "Narayan S, et al. Pharmaceutical Biology. 2007;45:468."}, {"Citation": "Rao JR, et al. Ind J Chem. 1989;28:199."}, {"Citation": "Rao JR, Rao PS. Ind J Chem. 1991;30:66."}, {"Citation": "Sha Valli Khan PS, et al. Biologia Plantarum. 1999;42:177."}, {"Citation": "Rao BK, Rao CH. Phytomedicine. 2001;8:88.", "ArticleIdList": ["11315761"]}, {"Citation": "http://grande.nal.usda.gov/ibids/index.phpimporimiii"}, {"Citation": "http://www.progenebio.in/dmp/bmp.html"}]}], "History": [{"Year": "2007", "Month": "10", "Day": "27"}, {"Year": "2008", "Month": "11", "Day": "13"}, {"Year": "2008", "Month": "1", "Day": "21"}, {"Year": "2008", "Month": "3", "Day": "5", "Hour": "9", "Minute": "0"}, {"Year": "2008", "Month": "3", "Day": "5", "Hour": "9", "Minute": "1"}, {"Year": "2008", "Month": "3", "Day": "5", "Hour": "9", "Minute": "0"}, {"Year": "2008", "Month": "1", "Day": "1"}], "PublicationStatus": "epublish", "ArticleIdList": ["18317578", "PMC2258430", "10.6026/97320630002260"]}}], "PubmedBookArticle": []}