{"PubmedArticle": [{"MedlineCitation": {"KeywordList": [], "OtherID": [], "CitationSubset": ["IM"], "InvestigatorList": [], "SpaceFlightMission": [], "GeneralNote": [], "OtherAbstract": [], "PMID": "27141684", "DateCompleted": {"Year": "2016", "Month": "06", "Day": "30"}, "DateRevised": {"Year": "2016", "Month": "05", "Day": "03"}, "Article": {"ArticleDate": [], "ELocationID": [], "Language": ["chi"], "Journal": {"ISSN": "1001-5302", "JournalIssue": {"Volume": "40", "Issue": "23", "PubDate": {"Year": "2015", "Month": "Dec"}}, "Title": "Zhongguo Zhong yao za zhi = Zhongguo zhongyao zazhi = China journal of Chinese materia medica", "ISOAbbreviation": "Zhongguo Zhong Yao Za Zhi"}, "ArticleTitle": "[Analysis of varieties and standards of Scrophulariaceae plants used in Tibetan medicine].", "Pagination": {"StartPage": "4686", "EndPage": "4692", "MedlinePgn": "4686-92"}, "Abstract": {"AbstractText": ["In this paper, the popular domestic varieties and quality standard of Scrophulariaceae plants used in Tibetan medicine were analyzed. The results showed that there were 11 genera and 99 species (including varieties), as well as 28 medicinal materials varieties of Scrophulariaceae plants were recorded in the relevant literatures. In relevant Tibetan standards arid literatures, there are great differences in varieties, sources, parts, and efficacies of medicinal plant. Among them, about 41.4% (including 41 species) of endemic plants, about 15.2% (including 15 species) of the original plants have medicinal standard legal records, except the medicinal materials of Scrophalaria ningpoensis, Lagotis brevituba, Picrorhiza scrophulariiflora, Veronica eriogyne general, most varieties have not completed quality standard. Consequently it is necessary to reinforce the herbal textual, resources and the use present situation investigation, the effects of the species resources material foundation and biological activity, quality standard, specification the medical terms of the plants, and promote Tibetan medicinal vareties-terminologies-sources such as the criterion and quality standard system for enriching the varieties of Tibetan medicinal materials and Chinese medicinal resources."]}, "AuthorList": [{"Identifier": [], "AffiliationInfo": [], "LastName": "Cao", "ForeName": "Lan", "Initials": "L"}, {"Identifier": [], "AffiliationInfo": [], "LastName": "Mu", "ForeName": "Ze-jing", "Initials": "ZJ"}, {"Identifier": [], "AffiliationInfo": [], "LastName": "Zhong", "ForeName": "Wei-hong", "Initials": "WH"}, {"Identifier": [], "AffiliationInfo": [], "LastName": "Zhong", "ForeName": "Wei-jin", "Initials": "WJ"}, {"Identifier": [], "AffiliationInfo": [], "LastName": "He", "ForeName": "Jun-wei", "Initials": "JW"}, {"Identifier": [], "AffiliationInfo": [], "LastName": "Du", "ForeName": "Xiao-lang", "Initials": "XL"}, {"Identifier": [], "AffiliationInfo": [], "LastName": "Zhong", "ForeName": "Guo-yue", "Initials": "GY"}], "PublicationTypeList": ["English Abstract", "Journal Article", "Research Support, Non-U.S. Gov't"]}, "MedlineJournalInfo": {"Country": "China", "MedlineTA": "Zhongguo Zhong Yao Za Zhi", "NlmUniqueID": "8913656", "ISSNLinking": "1001-5302"}, "ChemicalList": [{"RegistryNumber": "0", "NameOfSubstance": "Drugs, Chinese Herbal"}], "MeshHeadingList": [{"QualifierName": ["chemistry", "pharmacology"], "DescriptorName": "Drugs, Chinese Herbal"}, {"QualifierName": [], "DescriptorName": "Humans"}, {"QualifierName": ["standards"], "DescriptorName": "Medicine, Tibetan Traditional"}, {"QualifierName": ["chemistry", "classification"], "DescriptorName": "Plants, Medicinal"}, {"QualifierName": ["chemistry", "classification"], "DescriptorName": "Scrophulariaceae"}]}, "PubmedData": {"ReferenceList": [], "History": [{"Year": "2016", "Month": "5", "Day": "5", "Hour": "6", "Minute": "0"}, {"Year": "2016", "Month": "5", "Day": "5", "Hour": "6", "Minute": "0"}, {"Year": "2016", "Month": "7", "Day": "1", "Hour": "6", "Minute": "0"}], "PublicationStatus": "ppublish", "ArticleIdList": ["27141684"]}}], "PubmedBookArticle": []}