{"PubmedArticle": [{"MedlineCitation": {"InvestigatorList": [], "SpaceFlightMission": [], "CitationSubset": ["IM"], "KeywordList": [], "GeneralNote": [], "OtherAbstract": [], "OtherID": [], "PMID": "6973341", "DateCompleted": {"Year": "1981", "Month": "09", "Day": "15"}, "DateRevised": {"Year": "2019", "Month": "06", "Day": "23"}, "Article": {"Language": ["eng"], "ELocationID": [], "ArticleDate": [], "Journal": {"ISSN": "0006-2952", "JournalIssue": {"Volume": "30", "Issue": "10", "PubDate": {"Year": "1981", "Month": "May", "Day": "15"}}, "Title": "Biochemical pharmacology", "ISOAbbreviation": "Biochem Pharmacol"}, "ArticleTitle": "Protective effects of semicarbazide and p-aminobenzoic acid against ozone toxicity.", "Pagination": {"StartPage": "1033", "EndPage": "1037", "MedlinePgn": "1033-7"}, "AuthorList": [{"AffiliationInfo": [], "Identifier": [], "LastName": "Verweij", "ForeName": "H", "Initials": "H"}, {"AffiliationInfo": [], "Identifier": [], "LastName": "van Steveninck", "ForeName": "J", "Initials": "J"}], "PublicationTypeList": ["Journal Article", "Research Support, Non-U.S. Gov't"]}, "MedlineJournalInfo": {"Country": "England", "MedlineTA": "Biochem Pharmacol", "NlmUniqueID": "0101032", "ISSNLinking": "0006-2952"}, "ChemicalList": [{"RegistryNumber": "0", "NameOfSubstance": "Aminobenzoates"}, {"RegistryNumber": "0", "NameOfSubstance": "Semicarbazides"}, {"RegistryNumber": "12634-43-4", "NameOfSubstance": "Spectrin"}, {"RegistryNumber": "66H7ZZK23N", "NameOfSubstance": "Ozone"}, {"RegistryNumber": "EC 2.7.1.1", "NameOfSubstance": "Hexokinase"}, {"RegistryNumber": "EC 3.1.1.7", "NameOfSubstance": "Acetylcholinesterase"}, {"RegistryNumber": "RWP5GA015D", "NameOfSubstance": "Potassium"}, {"RegistryNumber": "TL2TJE8QTX", "NameOfSubstance": "4-Aminobenzoic Acid"}], "MeshHeadingList": [{"QualifierName": ["pharmacology"], "DescriptorName": "4-Aminobenzoic Acid"}, {"QualifierName": ["blood"], "DescriptorName": "Acetylcholinesterase"}, {"QualifierName": ["pharmacology"], "DescriptorName": "Aminobenzoates"}, {"QualifierName": ["drug effects", "metabolism"], "DescriptorName": "Erythrocyte Membrane"}, {"QualifierName": ["metabolism"], "DescriptorName": "Erythrocytes"}, {"QualifierName": ["blood"], "DescriptorName": "Hexokinase"}, {"QualifierName": [], "DescriptorName": "Humans"}, {"QualifierName": [], "DescriptorName": "Kinetics"}, {"QualifierName": ["pharmacology"], "DescriptorName": "Ozone"}, {"QualifierName": ["blood"], "DescriptorName": "Potassium"}, {"QualifierName": ["pharmacology"], "DescriptorName": "Semicarbazides"}, {"QualifierName": ["metabolism"], "DescriptorName": "Spectrin"}]}, "PubmedData": {"ReferenceList": [], "History": [{"Year": "1981", "Month": "5", "Day": "15"}, {"Year": "1981", "Month": "5", "Day": "15", "Hour": "0", "Minute": "1"}, {"Year": "1981", "Month": "5", "Day": "15", "Hour": "0", "Minute": "0"}], "PublicationStatus": "ppublish", "ArticleIdList": ["6973341", "10.1016/0006-2952(81)90438-x", "0006-2952(81)90438-X"]}}], "PubmedBookArticle": []}